{
  "so_hieu": "thong-tu-so-39-2026-tt-btc-469256",
  "slug": "thong-tu-so-39-2026-tt-btc-469256",
  "loai": "Thông tư",
  "loai_priority": 3,
  "nam": 2026,
  "topic_key": "thue_tncn",
  "topic_name": "Thuế TNCN",
  "nguon_url": "https://congbao.chinhphu.vn/van-ban/thong-tu-so-39-2026-tt-btc-469256.htm",
  "pdf_url": "https://congbaocdn.chinhphu.vn/180507251028987904/2026/4/15/469256-1776236226_v1_1776238206_signed.pdf",
  "pdf_path": "docs/thue_tncn/thong-tu-so-39-2026-tt-btc-469256.pdf",
  "txt_path": "docs/thue_tncn/thong-tu-so-39-2026-tt-btc-469256.txt",
  "mo_ta": "Thuế TNCN",
  "full_text": "CÔNG BÁO/Số 216/Ngày 15-04-2026 \n88 \n \n \nBỘ TÀI CHÍNH \n \n \nSố: 39/2026/TT-BTC \n \nCỘNG HÒA XÃ HỘI CHỦ NGHĨA VIỆT NAM \nĐộc lập - Tự do - Hạnh phúc \n \nHà Nội, ngày 31 tháng 3 năm 2026 \n         \nTHÔNG TƯ \nQuy định mức thu, chế độ thu, nộp \nphí, lệ phí áp dụng tại cảng, bến thủy nội địa \n \nCăn cứ Luật Phí và lệ phí số 97/2015/QH13; \nCăn cứ Luật Ngân sách nhà nước số 89/2025/QH15; \nCăn cứ Luật Giao thông đường thủy nội địa số 23/2004/QH11 được sửa đổi, \nbổ sung bởi Luật số 48/2014/QH13; \nCăn cứ Nghị định số 362/2025/NĐ-CP của Chính phủ quy định chi tiết một \nsố điều và biện pháp để tổ chức, hướng dẫn thi hành Luật Phí và lệ phí; \nCăn cứ Nghị định số 08/2021/NĐ-CP của Chính phủ quy định về quản lý hoạt \nđộng đường thủy nội địa được sửa đổi, bổ sung bởi Nghị định số 06/2024/NĐ-CP; \nCăn cứ Nghị định số 29/2025/NĐ-CP của Chính phủ quy định chức năng, \nnhiệm vụ, quyền hạn và cơ cấu tổ chức của Bộ Tài chính được sửa đổi, bổ sung \nbởi Nghị định số 166/2025/NĐ-CP;  \nTheo đề nghị của Cục trưởng Cục Quản lý, giám sát chính sách thuế, phí và \nlệ phí; \nBộ trưởng Bộ Tài chính ban hành Thông tư quy định mức thu, chế độ thu, nộp \nphí, lệ phí áp dụng tại cảng, bến thủy nội địa. \nĐiều 1. Phạm vi điều chỉnh và đối tượng áp dụng \n1. Thông tư này quy định đối tượng chịu phí, lệ phí, tổ chức thu phí, lệ phí, \nđối tượng được miễn phí, lệ phí, mức thu, chế độ thu, nộp phí, lệ phí áp dụng tại \ncảng, bến thủy nội địa (bao gồm cả cảng, bến thủy nội địa chuyên dùng) bao gồm: \nphí trọng tải tàu, thuyền; phí trình báo đường thủy nội địa; phí bảo đảm hàng hải thu \nđối với tàu biển; lệ phí ra, vào cảng, bến thủy nội địa.  \n2. Trường hợp điều ước quốc tế mà nước Cộng hòa xã hội chủ nghĩa Việt \nNam là thành viên có quy định về phí, lệ phí áp dụng tại cảng, bến thủy nội địa \nKý bởi: CÔNG BÁO NƯỚC CỘNG HÒA XÃ HỘI CHỦ NGHĨA VIỆT NAM\nCơ quan: VĂN PHÒNG CHÍNH PHỦ\nNgày ký: 2026-04-15 14:30:07 +07:00\n\nCÔNG BÁO/Số 216/Ngày 15-04-2026 \n89 \n \n \nkhác với quy định tại Thông tư này thì thực hiện theo quy định của điều ước quốc \ntế đó. \n3. Thông tư này áp dụng đối với đối tượng chịu phí, lệ phí, tổ chức thu phí, lệ \nphí và cơ quan nhà nước, tổ chức, cá nhân khác có liên quan đến thu, nộp phí, lệ phí \náp dụng tại cảng, bến thủy nội địa. \nĐiều 2. Đối tượng chịu phí, lệ phí và tổ chức thu phí, lệ phí   \n1. Đối tượng chịu phí, lệ phí áp dụng tại cảng, bến thủy nội địa là các phương \ntiện thủy nội địa, thủy phi cơ, phương tiện thủy nước ngoài, tàu biển (sau đây gọi là \nphương tiện) ra, vào hoạt động tại các cảng, bến thủy nội địa đã được cơ quan có \nthẩm quyền công bố hoạt động, trừ trường hợp không thu phí, lệ phí quy định \ntại khoản 2 Điều này và đối tượng được miễn phí, lệ phí quy định tại Điều 3 Thông \ntư này.  \n2. Không thu phí trọng tải tàu, thuyền và lệ phí ra, vào cảng, bến thủy nội địa \nđối với các phương tiện mang cấp đăng kiểm VR-SI, VR-SII và VR-SIII (trừ các \nphương tiện mang cấp đăng kiểm VR-SI, VR-SII và VR-SIII xuất cảnh, nhập cảnh, \nquá cảnh; các phương tiện mang cấp đăng kiểm VR-SI, VR-SII và VR-SIII xuất \ncảnh, nhập cảnh, quá cảnh chịu phí, lệ phí theo mức thu quy định tại Điều 4 Thông \ntư này). \nTrường hợp phương tiện mang đồng thời cấp đăng kiểm VR-SB và cấp đăng \nkiểm VR-SI, VR-SII và VR-SIII thì áp dụng mức thu phí, lệ phí như đối với phương \ntiện mang cấp đăng kiểm VR-SB. \n3. Cơ quan nhà nước, đơn vị sự nghiệp công lập có thẩm quyền quản lý nhà \nnước về hàng hải và đường thủy nội địa tại cảng, bến thủy nội địa, tổ chức được cơ \nquan nhà nước có thẩm quyền giao thực hiện nhiệm vụ quản lý tại cảng, bến thủy \nnội địa và cơ quan xác nhận việc trình báo đường thủy nội địa theo quy định của \npháp luật về đường thủy nội địa là tổ chức thu phí, lệ phí theo quy định tại Thông \ntư này. \nĐiều 3. Đối tượng được miễn phí, lệ phí \nMiễn phí, lệ phí áp dụng tại cảng, bến thủy nội địa đối với các trường hợp sau: \n1. Phương tiện thuộc Bộ Quốc phòng và Bộ Công an sử dụng vào mục đích \nquốc phòng, an ninh (trừ các phương tiện sử dụng vào hoạt động kinh tế); phương \ntiện của cơ quan hải quan đang làm nhiệm vụ; phương tiện của cảng vụ đường thủy \nnội địa, cảng vụ hàng hải, cơ quan quản lý nhà nước khác khi thực hiện công vụ.  \n2. Phương tiện tránh bão, cấp cứu.  \n\nCÔNG BÁO/Số 216/Ngày 15-04-2026 \n90 \n \n \n3. Phương tiện vận chuyển hàng hóa có trọng tải toàn phần dưới 10 tấn hoặc \nchở khách dưới 13 ghế.  \n4. Phương tiện vận chuyển người, hàng hóa, vật tư, trang thiết bị phòng chống \nlụt bão, phương tiện tìm kiếm, cứu nạn, cứu hộ. \nĐiều 4. Mức thu phí, lệ phí \n1. Mức thu phí, lệ phí áp dụng tại cảng, bến thủy nội địa như sau: \nSố thứ \ntự \nNội dung khoản thu \nMức thu \n1 \nPhí trọng tải tàu, thuyền \na) \nLượt vào (kể cả có tải, không tải) \n165 đồng/tấn \ntrọng tải toàn \nphần \nb) \nLượt ra (kể cả có tải, không tải) \n165 đồng/tấn \ntrọng tải toàn \nphần \n2 \nLệ phí ra, vào cảng, bến thủy nội địa \n \na) \nPhương tiện chở hàng có trọng tải toàn phần từ 10 tấn đến 50 \ntấn \n5.000 \nđồng/chuyến \nb) \nPhương tiện chở hàng có trọng tải toàn phần trên 50 tấn đến \n200 tấn hoặc chở khách có sức chở từ 13 ghế đến 50 ghế \n10.000 \nđồng/chuyến \nc) \nPhương tiện chở hàng, đoàn lai có trọng tải toàn phần trên 200 \ntấn đến 500 tấn hoặc chở khách có sức chở từ 51 ghế đến 100 \nghế \n20.000 \nđồng/chuyến \nd) \nPhương tiện chở hàng, đoàn lai có trọng tải toàn phần trên 500 \ntấn đến 1.000 tấn hoặc chở khách từ 101 ghế trở lên \n30.000 \nđồng/chuyến \nđ) \nPhương tiện chở hàng, đoàn lai có trọng tải toàn phần trên \n1.000 tấn đến 1.500 tấn \n40.000 \nđồng/chuyến \ne) \nPhương tiện chở hàng, đoàn lai có trọng tải toàn phần trên \n1.500 tấn \n50.000 \nđồng/chuyến \n3 \nPhí trình báo đường thủy nội địa \n \na) \nTàu biển, thủy phi cơ \n100.000 đồng/lần \n\nCÔNG BÁO/Số 216/Ngày 15-04-2026 \n91 \n \n \nSố thứ \ntự \nNội dung khoản thu \nMức thu \nb) \nPhương tiện thủy nội địa, phương tiện thủy nước ngoài: \nPhương tiện không có động cơ trọng tải toàn phần từ 10 tấn \ntrở lên; phương tiện có động cơ tổng công suất máy chính từ \n10 sức ngựa trở lên; phương tiện có sức chở trên 12 người \n50.000 đồng/lần \n2. Đối với tàu biển ra, vào cảng, bến thủy nội địa phải chịu phí, lệ phí (bao \ngồm cả phí bảo đảm hàng hải) theo Biểu mức thu phí, lệ phí hàng hải do Bộ Tài \nchính ban hành. \n3. Trường hợp trong cùng một chuyến đi, phương tiện ra, vào nhiều cảng, bến \nthủy nội địa thuộc cùng một đại diện cảng vụ quản lý chỉ phải chịu một lần phí, lệ \nphí theo quy định tại khoản 1 Điều này. \n4. Phương tiện ra, vào cảng, bến thủy nội địa không nhằm mục đích bốc dỡ \nhàng hóa, không nhận trả khách áp dụng mức thu phí trọng tải tàu, thuyền bằng \n70% (bảy mươi phần trăm) mức thu phí trọng tải tàu, thuyền quy định tại khoản 1 \nĐiều này. \n5. Đối với các phương tiện không có trọng tải toàn phần được quy đổi khi tính \nphí trọng tải tàu, thuyền như sau: \na) Phương tiện chuyên dùng: 01 sức ngựa tương đương với 01 tấn trọng tải \ntoàn phần; \nb) Phương tiện chở khách: 01 giường nằm tương đương với 06 ghế hành khách \nhoặc tương đương với 06 tấn trọng tải toàn phần; 01 ghế hoặc 01 hành khách tương \nđương với 01 tấn trọng tải toàn phần; 01 tấn sức nâng của cẩu đặt trên phương tiện \nquy đổi tương đương với 09 tấn trọng tải toàn phần; \nc) Đối với đoàn lai: Tính bằng tổng trọng tải toàn phần của các phương tiện \nbị lai; \nd) Đối với tàu thủy ra, vào cảng, bến thủy nội địa để sửa chữa, phá dỡ hoặc \nhạ thủy: Tính bằng 50% trọng tải lớn nhất ghi trong giấy chứng nhận của cơ quan \nđăng kiểm; \nđ) Trọng tải sau khi quy đổi là tấn: Phần lẻ dưới 0,5 tấn không tính, từ 0,5 tấn \ntrở lên tính tròn là 01 tấn; \ne) Đối với phương tiện chở chất lỏng: 01 m3 được tính tương đương là 01 tấn \ntrọng tải toàn phần; \ng) Đối với thủy phi cơ: 01 sức ngựa (HP, CV) tính bằng 0,5 GT; 01 GT bằng \n1,5 tấn trọng tải toàn phần. \n\nCÔNG BÁO/Số 216/Ngày 15-04-2026 \n92 \n \n \nTrường hợp việc quy đổi theo các phương thức quy định tại khoản này có kết \nquả khác nhau thì lấy theo phương thức quy đổi có trọng tải toàn phần lớn nhất. \nĐiều 5. Khai, thu, nộp phí, lệ phí và quyết toán phí \n1. Tổ chức thu phí, lệ phí nộp 100% số tiền phí, lệ phí thu được vào ngân sách \nnhà nước theo chương, tiểu mục của Mục lục ngân sách nhà nước hiện hành.  \nNguồn chi phí trang trải cho việc thu phí, lệ phí được ngân sách nhà nước bố \ntrí trong dự toán của tổ chức thu phí, lệ phí theo chế độ, định mức chi ngân sách nhà \nnước theo quy định của pháp luật.  \n2. Phí, lệ phí áp dụng tại cảng, bến thủy nội địa thu bằng đồng Việt Nam. \nTrường hợp thu phí, lệ phí từ tổ chức, cá nhân nước ngoài bằng ngoại tệ thì thu bằng \nđô la Mỹ (USD) trên cơ sở quy đổi theo tỷ giá quy định tại khoản 7 Điều 3 Nghị \nđịnh số 362/2025/NĐ-CP ngày 31 tháng 12 năm 2025 của Chính phủ quy định chi \ntiết một số điều và biện pháp để tổ chức, hướng dẫn thi hành Luật Phí và lệ phí. \n3. Tổ chức thu phí, lệ phí khai, thu, nộp phí, lệ phí và quyết toán phí theo quy \nđịnh tại Điều 3 Nghị định số 362/2025/NĐ-CP. \nĐiều 6. Hiệu lực thi hành \n1. Thông tư này có hiệu lực kể từ ngày 01 tháng 4 năm 2026 và thay thế Thông \ntư số 248/2016/TT-BTC ngày 11 tháng 11 năm 2016 của Bộ trưởng Bộ Tài chính \nquy định mức thu, chế độ thu, nộp, quản lý và sử dụng phí, lệ phí áp dụng tại cảng, \nbến thủy nội địa. \n2. Các nội dung khác liên quan đến việc thu, nộp, chứng từ thu, công khai chế \nđộ thu phí, lệ phí không quy định tại Thông tư này được thực hiện theo quy định tại \ncác văn bản: Luật Phí và lệ phí số 97/2015/QH13; Nghị định số 362/2025/NĐ-CP; \nLuật Quản lý thuế số 38/2019/QH14; Nghị định số 126/2020/NĐ-CP ngày 19 tháng \n10 năm 2020 của Chính phủ quy định chi tiết một số điều của Luật Quản lý thuế \nđược sửa đổi, bổ sung bởi Nghị định số 91/2022/NĐ-CP và Nghị định số \n373/2025/NĐ-CP; Nghị định số 347/2025/NĐ-CP ngày 29 tháng 12 năm 2025 của \nChính phủ quy định về thủ tục hành chính thuộc lĩnh vực Kho bạc Nhà nước; Nghị \nđịnh số 123/2020/NĐ-CP ngày 19 tháng 10 năm 2020 của Chính phủ quy định về \nhóa đơn, chứng từ được sửa đổi, bổ sung bởi Nghị định số 70/2025/NĐ-CP và Thông \ntư số 32/2025/TT-BTC ngày 31 tháng 5 năm 2025 của Bộ trưởng Bộ Tài \nchính hướng dẫn thực hiện một số điều của Luật Quản lý thuế ngày 13 tháng 6 năm \n2019, Nghị định số 123/2020/NĐ-CP ngày 19 tháng 10 năm 2020 của Chính phủ \nquy định về hóa đơn, chứng từ, Nghị định số 70/2025/NĐ-CP ngày 20 tháng 3 năm \n2025 sửa đổi, bổ sung một số điều của Nghị định số 123/2020/NĐ-CP.   \n\nCÔNG BÁO/Số 216/Ngày 15-04-2026 \n93 \n \n \n3. Trường hợp các văn bản quy phạm pháp luật quy định viện dẫn tại Thông \ntư này được sửa đổi, bổ sung hoặc thay thế thì thực hiện theo văn bản sửa đổi, bổ \nsung hoặc thay thế đó.  \n4. Trong quá trình thực hiện, nếu có vướng mắc đề nghị cơ quan, tổ chức, cá \nnhân phản ánh về Bộ Tài chính để nghiên cứu, hướng dẫn./. \n \nKT. BỘ TRƯỞNG \n \nTHỨ TRƯỞNG \n \nCao Anh Tuấn \n \n",
  "crawled_at": "2026-06-29 21:51"
}